README.md
setup.cfg
setup.py
aefReader/Reader.py
aefReader/__init__.py
aefReader/error.py
aefReader.egg-info/PKG-INFO
aefReader.egg-info/SOURCES.txt
aefReader.egg-info/dependency_links.txt
aefReader.egg-info/not-zip-safe
aefReader.egg-info/top_level.txt