Metadata-Version: 2.1
Name: aefReader
Version: 1-0
Summary: reading .aef files
Home-page: UNKNOWN
Author: Savtis
Author-email: 4dcubeoff@gmail.com
License: UNKNOWN
Platform: UNKNOWN
